syncra/__init__.py
tests/__init__.py
tests/test_sync_async.py
syncra-1.0.3.dist-info/METADATA
syncra-1.0.3.dist-info/WHEEL
syncra-1.0.3.dist-info/top_level.txt
syncra-1.0.3.dist-info/RECORD
