Metadata-Version: 2.1
Name: syncra
Version: 1.0.3
Summary: A utility for creating synchronous and asynchronous compatible methods.
Author-email: Islati // Skreet Media Inc // Wogwon Society <islati@wogwon.com>
Project-URL: Homepage, https://github.com/islati/syncra
Classifier: Programming Language :: Python :: 3
Classifier: License :: OSI Approved :: MIT License
Classifier: Operating System :: OS Independent
Requires-Python: >=3.6
Provides-Extra: dev
Requires-Dist: pytest; extra == "dev"
Requires-Dist: pytest-asyncio; extra == "dev"
Requires-Dist: pytest-cov; extra == "dev"
Requires-Dist: twine; extra == "dev"
